bscampp/__init__.py
bscampp/configs.py
bscampp/default.config
bscampp/functions.py
bscampp/init_configs.py
bscampp/jobs.py
bscampp/pipeline.py
bscampp/utils.py
bscampp/tools/epa-ng
bscampp/tools/pplacer
bscampp/tools/hamming_distance/CMakeLists.txt
bscampp/tools/hamming_distance/fragment_hamming
bscampp/tools/hamming_distance/hamming
bscampp/tools/hamming_distance/homology
bscampp/tools/hamming_distance/src/fragment_hamming.cpp
bscampp/tools/hamming_distance/src/fragment_tree_hamming.cpp
bscampp/tools/hamming_distance/src/fragment_tree_hamming_new.cpp
bscampp/tools/hamming_distance/src/homology.cpp
bscampp/tools/hamming_distance/src/new_hamming.cpp
bscampp-1.0.8.dist-info/licenses/LICENSE
bscampp-1.0.8.dist-info/METADATA
bscampp-1.0.8.dist-info/WHEEL
bscampp-1.0.8.dist-info/entry_points.txt
bscampp-1.0.8.dist-info/top_level.txt
bscampp-1.0.8.dist-info/RECORD
