Metadata-Version: 2.4
Name: bscampp
Version: 1.0.8
Summary: BSCAMPP and SCAMPP - Scalable Phylogenetic Placement Tools
Author-email: Eleanor Wedell <ewedell2@illinois.edu>, Chengze Shen <chengze5@illinois.edu>
License: MIT License
Project-URL: Homepage, https://github.com/ewedell/BSCAMPP
Project-URL: Changelog, https://github.com/ewedell/BSCAMPP/CHANGELOG.md
Classifier: Development Status :: 4 - Beta
Classifier: Operating System :: OS Independent
Classifier: Intended Audience :: Developers
Classifier: Intended Audience :: Science/Research
Classifier: Topic :: Scientific/Engineering :: Bio-Informatics
Classifier: Topic :: Software Development
Classifier: License :: OSI Approved :: GNU General Public License (GPL)
Classifier: Programming Language :: Python
Classifier: Programming Language :: Python :: 3
Classifier: Programming Language :: Python :: 3.7
Classifier: Programming Language :: Python :: 3.8
Classifier: Programming Language :: Python :: 3.9
Classifier: Programming Language :: Python :: 3.10
Classifier: Programming Language :: Python :: 3.11
Classifier: Programming Language :: Python :: 3.12
Requires-Python: >=3.7
License-File: LICENSE
Requires-Dist: ConfigParser>=5.0.0
Requires-Dist: numpy>=1.21.6
Requires-Dist: treeswift>=1.1.45
Requires-Dist: taxtastic>=0.9.3
Dynamic: license-file
